LICENSE
MANIFEST.in
README.md
setup.py
simpleirc/__init__.py
simpleirc/callbacks.py
simpleirc/connection.py
simpleirc/fsm.py
simpleirc/io.py
simpleirc/irc.py
simpleirc/parser.py
simpleirc/state.py
simpleirc.egg-info/PKG-INFO
simpleirc.egg-info/SOURCES.txt
simpleirc.egg-info/dependency_links.txt
simpleirc.egg-info/entry_points.txt
simpleirc.egg-info/not-zip-safe
simpleirc.egg-info/top_level.txt