Metadata-Version: 1.0
Name: simpleirc
Version: 0.0.1
Summary: A simple IRC library.
Home-page: https://github.com/maxcountryman/simpleirc
Author: Max Countryman
Author-email: maxc@me.com
License: BSD
Platform: any
Classifier: Development Status :: 3 - Alpha
Classifier: Intended Audience :: Developers
Classifier: Programming Language :: Python
Classifier: License :: OSI Approved :: BSD License
Classifier: Operating System :: OS Independent
Classifier: Topic :: Software Development :: Libraries :: Python Modules
